{
  "profile": [
    {
      "Name": "vishal",
      "Phone": "+29911280083",
      "Company_Name": "Vishal pvt ltd",
      "county_Name": "Mauritania",
      "id": 1
    },
    {
      "Name": "vishal",
      "Phone": "+29911280083",
      "Company_Name": "Vishal pvt ltd",
      "county_Name": "Mauritania",
      "id": 2
    },
    {
      "Name": "vishal",
      "Phone": "+29911280083",
      "Company_Name": "Vishal pvt ltd",
      "county_Name": "Mauritania",
      "id": 3
    },
    {
      "Name": "vishal",
      "Phone": "+29911280083",
      "Company_Name": "Vishal pvt ltd",
      "county_Name": "Mauritania",
      "id": 4
    },
    {
      "Name": "vishal",
      "Phone": "+29911280083",
      "Company_Name": "Vishal pvt ltd",
      "county_Name": "Mauritania",
      "id": 5
    },
    {
      "Name": "vishal",
      "Phone": "+29911280083",
      "Company_Name": "Vishal pvt ltd",
      "county_Name": "Mauritania",
      "id": 6
    },
    {
      "Phone": "+2undefined",
      "county_Name": "Mauritania",
      "id": 7
    },
    {
      "Name": "vishal",
      "Phone": "+29911280083",
      "Company_Name": "Vishal pvt ltd",
      "county_Name": "India",
      "id": 8
    },
    {
      "Name": "vishal",
      "Phone": "+29911280083",
      "Company_Name": "Vishal pvt ltd",
      "county_Name": "Mauritania",
      "id": 9
    },
    {
      "This_week": "week",
      "Next_month": "month",
      "Next_year": "year",
      "First_Task": "first",
      "Second_Task": "secon",
      "Third_Task": "third",
      "project": "peoject",
      "space": "space",
      "team": "IT",
      "Job_role": "software",
      "Name": "vishal",
      "Phone": "+29911280083",
      "Company_Name": "Vishal pvt ltd",
      "county_Name": "Mauritania",
      "id": 10
    }
  ]
}